temporaliox/__init__.py
temporaliox/activity.py
temporaliox-0.3.0.dist-info/licenses/LICENSE
temporaliox-0.3.0.dist-info/WHEEL
temporaliox-0.3.0.dist-info/METADATA
temporaliox-0.3.0.dist-info/RECORD
