Metadata-Version: 2.4
Name: temporaliox
Version: 0.3.0
Summary: A helper library for Temporal.io that enables separation of activity declarations from implementations
Author: Igor Kozyrenko
Requires-Python: >=3.9
Classifier: Development Status :: 4 - Beta
Classifier: Intended Audience :: Developers
Classifier: License :: OSI Approved :: MIT License
Classifier: Operating System :: OS Independent
Classifier: Programming Language :: Python :: 3
Classifier: Programming Language :: Python :: 3.9
Classifier: Programming Language :: Python :: 3.10
Classifier: Programming Language :: Python :: 3.11
Classifier: Programming Language :: Python :: 3.12
Classifier: Programming Language :: Python :: 3.13
Classifier: Topic :: Software Development :: Libraries :: Python Modules
Classifier: Topic :: System :: Distributed Computing
License-File: LICENSE
Requires-Dist: temporalio>=1.5.0
Requires-Dist: pytest>=8.0.0 ; extra == "dev"
Requires-Dist: pytest-asyncio>=0.23.0 ; extra == "dev"
Requires-Dist: ruff>=0.1.0 ; extra == "dev"
Requires-Dist: black>=23.0.0 ; extra == "dev"
Requires-Dist: build>=0.10.0 ; extra == "dev"
Project-URL: Homepage, https://github.com/ikseek/temporaliox
Project-URL: Repository, https://github.com/ikseek/temporaliox
Provides-Extra: dev
